{
  "dataset": "law",
  "instance_idx": 173,
  "prompt_type": "narrative",
  "provider": "grok",
  "model": "grok-4-1-fast-non-reasoning",
  "timestamp": "2026-04-16T14:38:56.410689",
  "status": "success",
  "narrative": "Dear [Student's Name], I know this rejection letter stings—dreaming of law school and then hearing no must feel like a door slamming shut just as you're reaching for the handle. Our model looked at your profile and saw a 45% chance of struggling to pass the bar exam down the line, which is why it flagged your application as too risky for admission. What stood out most was your Year 3 decile of 1.0, placing you at the very bottom of your class that year, and that was the biggest signal pulling toward this tough prediction—it suggested the rigors of advanced legal studies might prove an uphill battle. Your Year 1 decile of 4.0 reinforced that concern, showing your grades hadn't climbed as they'd hoped for someone aiming high in law. Layered on top was your LSAT score of 32.0, which, while respectable, didn't quite signal the standout analytical firepower the model associates with bar success. Even your upper-middle family income, which can open doors for many, worked against you here, as the model links it to patterns where students sometimes coast rather than grind through the bar's demands. Your Asian background, undergraduate GPA of 3.0, full-time study plans, and being female each added their own subtle nudges toward failure in the model's view, painting a picture of someone whose path might hit unexpected roadblocks. It's not that you're incapable—far from it—but together, these pieces formed a story of potential mismatch with the intense bar prep ahead. The good news? This isn't set in stone; with targeted improvements like boosting those deciles or retaking the LSAT, you could rewrite your story entirely. You've got the drive to target law school, and that's huge—keep pushing, because models predict patterns, but you write your future. Hang in there; brighter paths await.",
  "error": null
}